MANIFEST.in
README.rst
eha-epg-search.py
eha-movie-list.py
eha-service-list.py
eha-timer-list.py
eha-utility-belt.py
setup.cfg
setup.py
versioneer.py
enigma2_http_api/__init__.py
enigma2_http_api/_version.py
enigma2_http_api/controller.py
enigma2_http_api/defaults.py
enigma2_http_api/example_data.py
enigma2_http_api/model.py
enigma2_http_api/utils.py
enigma2_http_api.egg-info/PKG-INFO
enigma2_http_api.egg-info/SOURCES.txt
enigma2_http_api.egg-info/dependency_links.txt
enigma2_http_api.egg-info/requires.txt
enigma2_http_api.egg-info/top_level.txt