Metadata-Version: 1.0
Name: enigma2-http-api
Version: 0.3.5
Summary: enigma2 HTTP API client library
Home-page: https://github.com/doubleO8/enigma2_http_api
Author: doubleO8
Author-email: wb008@hdm-stuttgart.de
License: UNKNOWN
Platform: UNKNOWN
